LICENSE.txt
README.md
shazamio/__init__.py
shazamio/algorithm.py
shazamio/api.py
shazamio/client.py
shazamio/converter.py
shazamio/deprecated/__init__.py
shazamio/deprecated/decorator.py
shazamio/enums.py
shazamio/exceptions.py
shazamio/factory.py
shazamio/factory_misc.py
shazamio/interfaces/__init__.py
shazamio/interfaces/client.py
shazamio/loggers.py
shazamio/misc.py
shazamio/schemas/__init__.py
shazamio/schemas/artist/__init__.py
shazamio/schemas/artist/views/__init__.py
shazamio/schemas/artist/views/full_albums.py
shazamio/schemas/artist/views/last_release.py
shazamio/schemas/artist/views/simular_artists.py
shazamio/schemas/artist/views/top_music.py
shazamio/schemas/artist/views/top_song.py
shazamio/schemas/artists.py
shazamio/schemas/attributes.py
shazamio/schemas/base.py
shazamio/schemas/enums.py
shazamio/schemas/errors.py
shazamio/schemas/models.py
shazamio/schemas/photos.py
shazamio/schemas/urls.py
shazamio/serializers.py
shazamio/signature.py
shazamio/typehints.py
shazamio/user_agent.py
shazamio/utils.py
shazamio-0.5.1.dist-info/LICENSE.txt
shazamio-0.5.1.dist-info/METADATA
shazamio-0.5.1.dist-info/WHEEL
shazamio-0.5.1.dist-info/RECORD
